arlbench/__init__.py
arlbench/arlbench.py
arlbench/autorl/__init__.py
arlbench/autorl/autorl_env.py
arlbench/autorl/checkpointing.py
arlbench/autorl/objectives.py
arlbench/autorl/state_features.py
arlbench/core/__init__.py
arlbench/core/running_statistics.py
arlbench/core/algorithms/__init__.py
arlbench/core/algorithms/algorithm.py
arlbench/core/algorithms/buffers.py
arlbench/core/algorithms/common.py
arlbench/core/algorithms/prioritised_item_buffer.py
arlbench/core/algorithms/dqn/__init__.py
arlbench/core/algorithms/dqn/dqn.py
arlbench/core/algorithms/dqn/models.py
arlbench/core/algorithms/ppo/__init__.py
arlbench/core/algorithms/ppo/models.py
arlbench/core/algorithms/ppo/ppo.py
arlbench/core/algorithms/sac/__init__.py
arlbench/core/algorithms/sac/models.py
arlbench/core/algorithms/sac/sac.py
arlbench/core/environments/__init__.py
arlbench/core/environments/autorl_env.py
arlbench/core/environments/brax_env.py
arlbench/core/environments/envpool_env.py
arlbench/core/environments/gymnasium_env.py
arlbench/core/environments/gymnax_env.py
arlbench/core/environments/make_env.py
arlbench/core/environments/xland_env.py
arlbench/core/wrappers/__init__.py
arlbench/core/wrappers/flatten_observation.py
arlbench/core/wrappers/wrapper.py
arlbench/utils/__init__.py
arlbench/utils/common.py
tests/autorl/__init__.py
tests/autorl/test_autorl_env.py
tests/autorl/test_checkpointing.py
tests/autorl/test_objectives.py
tests/core/__init__.py
tests/core/algorithms/__init__.py
tests/core/algorithms/test_dqn.py
tests/core/algorithms/test_ppo.py
tests/core/algorithms/test_sac.py
tests/utils/__init__.py
tests/utils/test_utils.py
ARLBench-0.1.3.dist-info/AUTHORS.md
ARLBench-0.1.3.dist-info/LICENSE
ARLBench-0.1.3.dist-info/METADATA
ARLBench-0.1.3.dist-info/WHEEL
ARLBench-0.1.3.dist-info/top_level.txt
ARLBench-0.1.3.dist-info/RECORD
