Metadata-Version: 2.1
Name: ARLBench
Version: 0.1.3
Summary: Python Boilerplate that contains all the code you need to create a Python package.
Author-email: AutoML Hannover <automl@ai.uni-hannover.de>
License: 
Classifier: Intended Audience :: Science/Research
Classifier: Intended Audience :: Developers
Classifier: License :: OSI Approved :: BSD License
Classifier: Programming Language :: Python
Classifier: Topic :: Software Development
Classifier: Topic :: Scientific/Engineering
Classifier: Operating System :: POSIX
Classifier: Operating System :: Unix
Classifier: Programming Language :: Python :: 3
Requires-Python: >=3.10
License-File: LICENSE
License-File: AUTHORS.md
Requires-Dist: typing-extensions
Requires-Dist: tomli ==2.0.1
Requires-Dist: pre-commit ==3.7.0
Requires-Dist: codecarbon ==2.3.5
Requires-Dist: memray ==1.12.0
Requires-Dist: pathos ==0.3.2
Requires-Dist: jax ==0.4.26
Requires-Dist: jaxlib ==0.4.26
Requires-Dist: flashbax ==0.1.2
Requires-Dist: gymnax ==0.0.6
Requires-Dist: chex ==0.1.86
Requires-Dist: ConfigSpace ==0.7.1
Requires-Dist: distrax ==0.1.5
Requires-Dist: flax ==0.8.2
Requires-Dist: brax ==0.10.3
Requires-Dist: pytest ==7.4.4
Requires-Dist: coverage ==7.4.4
Requires-Dist: ruff
Requires-Dist: hydra-core
Requires-Dist: hydra-submitit-launcher
Requires-Dist: hydra-colorlog
Requires-Dist: mypy
Requires-Dist: tox
Requires-Dist: twine
Requires-Dist: bump-my-version
Provides-Extra: dev
Requires-Dist: ARLBench[doc,examples,test,tooling] ; extra == 'dev'
Provides-Extra: doc
Requires-Dist: automl-sphinx-theme ; extra == 'doc'
Provides-Extra: envpool
Requires-Dist: envpool ==0.8.4 ; extra == 'envpool'
Provides-Extra: examples
Requires-Dist: hypersweeper ; extra == 'examples'
Provides-Extra: test
Requires-Dist: pytest ; extra == 'test'
Requires-Dist: pytest-coverage ; extra == 'test'
Requires-Dist: pytest-cases ; extra == 'test'
Requires-Dist: ARLBench[examples] ; extra == 'test'
Provides-Extra: tooling
Requires-Dist: commitizen ; extra == 'tooling'
Requires-Dist: pre-commit ; extra == 'tooling'
Requires-Dist: ruff ; extra == 'tooling'
